aws_marketplace_ubuntu_scraper.py
setup.py
aws_marketplace_ubuntu_scraper-0.0.8.dist-info/LICENSE
aws_marketplace_ubuntu_scraper-0.0.8.dist-info/METADATA
aws_marketplace_ubuntu_scraper-0.0.8.dist-info/WHEEL
aws_marketplace_ubuntu_scraper-0.0.8.dist-info/entry_points.txt
aws_marketplace_ubuntu_scraper-0.0.8.dist-info/top_level.txt
aws_marketplace_ubuntu_scraper-0.0.8.dist-info/RECORD
