Metadata-Version: 2.1
Name: aws-marketplace-ubuntu-scraper
Version: 0.0.8
Summary: CLI to return the Ubuntu AMIs in AWS marketplace
Home-page: https://github.com/philroche/aws-marketplace-ubuntu-scraper
Author: Philip Roche
Author-email: phil.roche@canonical.com
License: GPLv3
Platform: UNKNOWN
Classifier: Development Status :: 2 - Pre-Alpha
Classifier: License :: OSI Approved :: GNU General Public License v3 (GPLv3)
Classifier: Programming Language :: Python
Classifier: Programming Language :: Python :: 3
Classifier: Programming Language :: Python :: 3.4
Classifier: Programming Language :: Python :: 3.5
Classifier: Programming Language :: Python :: 3.6
Classifier: Programming Language :: Python :: 3.7
Requires-Dist: boto3
Requires-Dist: click
Requires-Dist: pytest
Requires-Dist: selenium
Requires-Dist: selenium-wire
Requires-Dist: requests
Requires-Dist: beautifulsoup4
Requires-Dist: joblib
